LICENSE
MANIFEST.in
README.rst
setup.py
src/sentry_zabbix/__init__.py
src/sentry_zabbix/forms.py
src/sentry_zabbix/models.py
src/sentry_zabbix/plugin.py
src/sentry_zabbix.egg-info/PKG-INFO
src/sentry_zabbix.egg-info/SOURCES.txt
src/sentry_zabbix.egg-info/dependency_links.txt
src/sentry_zabbix.egg-info/entry_points.txt
src/sentry_zabbix.egg-info/not-zip-safe
src/sentry_zabbix.egg-info/requires.txt
src/sentry_zabbix.egg-info/top_level.txt