Metadata-Version: 1.1
Name: sentry-zabbix
Version: 0.0.13
Summary: A Sentry extension which send errors stats to Zabbix
Home-page: http://github.com/m0n5t3r/sentry-zabbix
Author: Sabin Iacob
Author-email: iacobs+pypi@gmail.com
License: WTFPL
Keywords: sentry zabbix
Platform: UNKNOWN
Classifier: Intended Audience :: Developers
Classifier: Intended Audience :: System Administrators
Classifier: Operating System :: OS Independent
Classifier: Programming Language :: Python
Classifier: Framework :: Django
Classifier: Topic :: Software Development
